setup.py
alfredo_distributions.egg-info/PKG-INFO
alfredo_distributions.egg-info/SOURCES.txt
alfredo_distributions.egg-info/dependency_links.txt
alfredo_distributions.egg-info/not-zip-safe
alfredo_distributions.egg-info/top_level.txt
distributions/Binomialdistribution.py
distributions/Gaussiandistribution.py
distributions/Generaldistribution.py
distributions/__init__.py